international_urns_es/__init__.py
international_urns_es/py.typed
international_urns_es/core/__init__.py
international_urns_es/core/cif.py
international_urns_es/core/dir3.py
international_urns_es/core/dni.py
international_urns_es/core/nie.py
international_urns_es/core/nif_klm.py
international_urns_es/core/nss.py
international_urns_es/core/plate.py
international_urns_es/core/provinces.py
international_urns_es/extractors/__init__.py
international_urns_es/extractors/cif.py
international_urns_es/extractors/dir3.py
international_urns_es/extractors/dni.py
international_urns_es/extractors/nie.py
international_urns_es/extractors/nif.py
international_urns_es/extractors/nif_klm.py
international_urns_es/extractors/nss.py
international_urns_es/extractors/plate.py
international_urns_es/generators/__init__.py
international_urns_es/generators/cif.py
international_urns_es/generators/dir3.py
international_urns_es/generators/dni.py
international_urns_es/generators/nie.py
international_urns_es/generators/nif.py
international_urns_es/generators/nif_klm.py
international_urns_es/generators/nss.py
international_urns_es/generators/plate.py
international_urns_es/integrations/__init__.py
international_urns_es/integrations/faker.py
international_urns_es/integrations/pydantic.py
international_urns_es/validators/__init__.py
international_urns_es/validators/cif.py
international_urns_es/validators/dir3.py
international_urns_es/validators/dni.py
international_urns_es/validators/nie.py
international_urns_es/validators/nif.py
international_urns_es/validators/nif_klm.py
international_urns_es/validators/nss.py
international_urns_es/validators/plate.py
international_urns_es-1.4.1.dist-info/METADATA
international_urns_es-1.4.1.dist-info/WHEEL
international_urns_es-1.4.1.dist-info/entry_points.txt
international_urns_es-1.4.1.dist-info/licenses/LICENSE
international_urns_es-1.4.1.dist-info/RECORD
