Metadata-Version: 2.4
Name: international-urns-es
Version: 1.4.1
Summary: Spain validator plugin for International URNs
Project-URL: Homepage, https://gitlab.com/Kencho1/international-urns-es
Project-URL: Repository, https://gitlab.com/Kencho1/international-urns-es
Project-URL: Issues, https://gitlab.com/Kencho1/international-urns-es/-/issues
Project-URL: Documentation, https://gitlab.com/Kencho1/international-urns-es/-/blob/main/README.md
Author: Jesús Alonso Abad
License: MIT
License-File: LICENSE
Keywords: cif,dni,matricula,nie,nif,nss,spain,urn,validation
Classifier: Development Status :: 5 - Production/Stable
Classifier: Intended Audience :: Developers
Classifier: License :: OSI Approved :: MIT License
Classifier: Programming Language :: Python :: 3
Classifier: Programming Language :: Python :: 3.11
Classifier: Programming Language :: Python :: 3.12
Classifier: Programming Language :: Python :: 3.13
Classifier: Topic :: Software Development :: Libraries :: Python Modules
Classifier: Typing :: Typed
Requires-Python: >=3.11
Requires-Dist: international-urns>=1.0.1
Provides-Extra: all
Requires-Dist: faker>=18.0.0; extra == 'all'
Requires-Dist: pydantic>=2.0.0; extra == 'all'
Provides-Extra: dev
Requires-Dist: mypy>=1.0.0; extra == 'dev'
Requires-Dist: pytest-cov>=4.0.0; extra == 'dev'
Requires-Dist: pytest>=7.0.0; extra == 'dev'
Requires-Dist: ruff>=0.1.0; extra == 'dev'
Provides-Extra: faker
Requires-Dist: faker>=18.0.0; extra == 'faker'
Provides-Extra: pydantic
Requires-Dist: pydantic>=2.0.0; extra == 'pydantic'
